nezha2/__init__.py
nezha2/core.py
nezha2/output_1x1.txt
nezha2/output_2x2.txt
nezha2/output_4x4.txt
nezha2-0.1.2.dist-info/METADATA
nezha2-0.1.2.dist-info/WHEEL
nezha2-0.1.2.dist-info/top_level.txt
nezha2-0.1.2.dist-info/RECORD
