Metadata-Version: 2.4
Name: NeZha2
Version: 0.1.2
Summary: 将二进制魔丸数据转换为GIF动画
Home-page: https://github.com/ququ85005702/NeZha2
Author: ququ
Author-email: 85005702@qq.com
License: MIT
Classifier: Programming Language :: Python :: 3
Classifier: License :: OSI Approved :: MIT License
Requires-Python: >=3.6
Dynamic: author
Dynamic: author-email
Dynamic: classifier
Dynamic: description-content-type
Dynamic: home-page
Dynamic: license
Dynamic: requires-python
Dynamic: summary
